ecco_access/__init__.py
ecco_access/ecco_acc_dates.py
ecco_access/ecco_access.py
ecco_access/ecco_download.py
ecco_access/ecco_s3_retrieve.py
ecco_access/ecco_varlist.py
ecco_access-0.2.1.dist-info/licenses/LICENSE
ecco_access-0.2.1.dist-info/METADATA
ecco_access-0.2.1.dist-info/WHEEL
ecco_access-0.2.1.dist-info/top_level.txt
ecco_access-0.2.1.dist-info/RECORD
