Metadata-Version: 2.4
Name: ecco_access
Version: 0.2.1
Summary: Access utilities for ECCO state estimate output hosted on PO.DAAC and in the AWS cloud
Author-email: ecco_access Developers <andrewdelman@ucla.edu>
Project-URL: Homepage, https://github.com/ECCO-GROUP/ECCO-ACCESS
Project-URL: Tracker, https://github.com/ECCO-GROUP/ECCO-ACCESS/issues
Keywords: ecco,climate,mitgcm,estimate,circulation,climate
Classifier: Development Status :: 5 - Production/Stable
Classifier: Intended Audience :: Science/Research
Classifier: Topic :: Scientific/Engineering
Classifier: Operating System :: OS Independent
Classifier: Programming Language :: Python
Classifier: Programming Language :: Python :: 3.7
Classifier: Programming Language :: Python :: 3.8
Classifier: Programming Language :: Python :: 3.9
Classifier: Programming Language :: Python :: 3.10
Classifier: Programming Language :: Python :: 3.11
Classifier: Programming Language :: Python :: 3.12
Classifier: Programming Language :: Python :: 3.13
Requires-Python: >=3.7
License-File: LICENSE
Requires-Dist: numpy
Requires-Dist: future
Requires-Dist: dask[complete]
Requires-Dist: fsspec>=2024.12.0
Requires-Dist: netCDF4
Requires-Dist: pandas
Requires-Dist: python-dateutil
Requires-Dist: requests
Requires-Dist: s3fs>=2024.12.0
Requires-Dist: tqdm
Requires-Dist: xarray
Requires-Dist: zarr>=3.0.7
Provides-Extra: dev
Requires-Dist: pytest; extra == "dev"
Requires-Dist: coverage; extra == "dev"
Dynamic: license-file
